Workbook

Sheet Changelog
A1: SteelBuild Pro Action Plan — Changelog
A3: As of | B3: 46228
A4: Source | B4: Updated from docs/action-plan/TASK_LEDGER.md + WORK_NEXT_SLICE.md (withProjectId) + merges #114–#121
A6: Key completions since 2026-07-23 workbook
A7: PR #114–#117: Piece Register restore, PMA removal, drawing/fab, piece-control, launch-readiness — on main + prod
A8: PR #119: Action-plan hygiene, LS-auth removal, mutation helpers, ResourceScheduling helpers, Sentry fixes — merged + prod deploy
A9: PR #120: TypeScript standard + priority business-rule TS conversions + check:no-new-js — merged + prod
A10: Hosted migrations applied including 20260724120000/130000/140000/150000
A11: Production: https://www.steelbuild-pro.com (deploy after #119)
A12: Remaining blockers: staging UAT credentials, GitHub Actions billing limit, large-page thinning, universal mutation adoption (ID 50)
A14: Status counts (Tracker)
A15: Done | B15: 79
A16: In Progress | B16: 25
A17: Blocked | B17: 1
A19: Total tasks | B19: 105
A21: 2026-07-25 next-slice: withProjectId write shaping on high-traffic creates; Done IDs 19/43/64/68/70/84/89/92/94/95/97/99/103-105
A22: 46229 | B22: cursor/action-plan-next-slice-d3a1 | C22: Adoption continuation: Submittals mutation helpers; withProjectId on CO/SOV/Procurement/Documents/Submittals; toUserErrorMessage on field/commercial toasts. IDs 21/48/50/52 remain Partial.
A23: 46229 | B23: cursor/action-plan-next-slice-d3a1 | C23: RFI mutation helpers (ID 23); withProjectId on ActionItems/DailyLogs/Constraints/LookAhead/WPs/FieldToday photos/EscalateModal/emailInbox.
A24: 46229 | B24: cursor/action-plan-next-slice-d3a1 | C24: Drawings mutation helpers (ID 27); withProjectId on FabRelease/ContractManagement/Schedule MPP import/comment dispositions/Deliveries alerts.
A25: 46229 | B25: PR #123 merged + prod deploy | C25: withProjectId + mutation helpers (Submittals/RFIs/Drawings) + tracker Done 78 / IP 26 / Blocked 1. Local gates green; GH Actions billing still blocked.
A31: 46229 | B31: cursor/action-plan-photos-safety-loading-d3a1 | C31: ID 18: Photos + Safety INLINE LoadingSkeleton + error/empty gates (no RegisterFetchBody dep; complements PR #133).
A32: 46229 | B32: field-loading | C32: Inspections INLINE gates + ProductionNote withProjectId; Done 79 / IP 25 / Blocked 1

Sheet Tracker
A1: ID | B1: Workstream | C1: Task | D1: Owner | E1: Priority | F1: Status | G1: Due Week | H1: Target Date | I1: Week Start | J1: Notes
A2: 1 | B2: Immediate Stabilization | C2: Identify every duplicated module under src/<module> and src/components/<module> | D2: Engineering | E2: Critical | F2: Done | G2: Week 1 | H2: 46228 | I2: 46228 | J2: Completed 2026-07-24. Duplicate inventory in docs/action-plan/DUPLICATE_INVENTORY.md (PR #119).
A3: 2 | B3: Immediate Stabilization | C3: Choose one canonical location for each duplicated file | D3: Engineering | E3: Critical | F3: Done | G3: Week 1 | H3: 46229 | I3: 46229 | J3: Completed 2026-07-24. Canonical ownership chosen; see DUPLICATE_INVENTORY.md + folder-ownership.md.
A4: 3 | B4: Immediate Stabilization | C4: Replace duplicate copies with imports/re-exports temporarily | D4: Engineering | E4: Critical | F4: Done | G4: Week 1 | H4: 46230 | I4: 46230 | J4: Completed 2026-07-24. Risky duplicates replaced with re-exports (e.g. ImpactBoard → Panel).
A5: 4 | B5: Immediate Stabilization | C5: Delete stale duplicate implementations after verification | D5: Engineering | E5: High | F5: Done | G5: Week 2 | H5: 46231 | I5: 46231 | J5: Completed 2026-07-24. Deleted dead viewer/**, WeeklySummary orphans, app-params.js, AuthCallbackError, BulkActionBar.
A6: 5 | B6: Immediate Stabilization | C6: Document final folder ownership rules | D6: Engineering | E6: High | F6: Done | G6: Week 2 | H6: 46232 | I6: 46232 | J6: Completed 2026-07-24. docs/architecture/folder-ownership.md published.
A7: 6 | B7: Broken Workflow Fixes | C7: Confirm task creation no longer causes disappearing records | D7: Engineering / QA | E7: Critical | F7: Done | G7: Week 1 | H7: 46233 | I7: 46233 | J7: Completed 2026-07-24. Task persistence sanitize + taskPersistence.test.ts (PR #119).
A8: 7 | B8: Broken Workflow Fixes | C8: Fix cost codes save behavior | D8: Engineering | E8: Critical | F8: Done | G8: Week 1 | H8: 46226 | I8: 46234 | J8: Completed earlier + re-verified. costCodeSave + soft-delete + unique index migration 20260724140000.
A9: 8 | B9: Broken Workflow Fixes | C9: Fix contracts save behavior | D9: Engineering | E9: Critical | F9: Done | G9: Week 1 | H9: 46226 | I9: 46235 | J9: Completed earlier + re-verified. ContractManagement + projectUpdateEvents.
A10: 9 | B10: Broken Workflow Fixes | C10: Fix change order edit behavior | D10: Engineering | E10: Critical | F10: Done | G10: Week 1 | H10: 46226 | I10: 46236 | J10: Completed earlier + re-verified. changeOrderPayload whitelist + tests.
A11: 10 | B11: Broken Workflow Fixes | C11: Fix change order delete behavior | D11: Engineering | E11: Critical | F11: Done | G11: Week 1 | H11: 46226 | I11: 46237 | J11: Completed earlier + re-verified. CO archive/soft-delete in CoControlCenter.
A12: 11 | B12: Broken Workflow Fixes | C12: Fix checklist item behavior | D12: Engineering | E12: Critical | F12: Done | G12: Week 1 | H12: 46226 | I12: 46238 | J12: Completed earlier + re-verified. closeoutPayload mapping + tests.
A13: 12 | B13: Broken Workflow Fixes | C13: Fix PMA nonfunctional paths | D13: Engineering | E13: Critical | F13: Done | G13: Week 1 | H13: 46226 | I13: 46239 | J13: Completed 2026-07-24. PMA removed from runtime (UI/routes/clients/tests); pmaRemoval.test.ts. Deployed to prod.
... A106: 105 | B106: Production Readiness | C106: Re-check UI trust and silent failure risk | D106: QA / PM | E106: High | F106: Done | G106: Week 5 | H106: 46332 | I106: 46332 | J106: Completed 2026-07-25 checkpoint. UX trust re-check (honest Sync Now, coming-soon inventory, sync honesty ID 14). Catalog future items intentional.

Sheet Summary
A1: SteelBuild Pro Action Plan Dashboard
A2: Plan start | B2: 46111.5 | C2: As of | D2: 46229 | E2: Completion | F2: =(COUNTIF(Tracker!$F$2:$F$106,"Done")+COUNTIF(Tracker!$F$2:$F$106,"QA Complete"))/COUNTA(Tracker!$C$2:$C$106) | G2: Open critical | H2: =COUNTIFS(Tracker!$E$2:$E$106,"Critical",Tracker!$F$2:$F$106,"<>Done",Tracker!$F$2:$F$106,"<>QA Complete")
A4: Total Tasks | C4: Completed | E4: In Progress | G4: Blocked
A5: =COUNTA(Tracker!$C$2:$C$106) | C5: =COUNTIF(Tracker!$F$2:$F$106,"Done") | E5: =COUNTIF(Tracker!$F$2:$F$106,"In Progress") | G5: =COUNTIF(Tracker!$F$2:$F$106,"Blocked")
A8: Not Started | C8: Ready for QA | E8: QA Complete | G8: Overdue Open
A9: =COUNTIF(Tracker!$F$2:$F$106,"Not Started") | C9: =COUNTIF(Tracker!$F$2:$F$106,"Ready for QA") | E9: =COUNTIF(Tracker!$F$2:$F$106,"QA Complete") | G9: =COUNTIFS(Tracker!$H$2:$H$106,"<"&TODAY(),Tracker!$F$2:$F$106,"<>Done",Tracker!$F$2:$F$106,"<>QA Complete")
A12: Workstream | B12: Task Count | C12: Critical | D12: High | E12: Medium | F12: Completed | G12: Open
A13: Backend Hardening | B13: =COUNTIF(Tracker!$B$2:$B$106,A13) | C13: =COUNTIFS(Tracker!$B$2:$B$106,A13,Tracker!$E$2:$E$106,"Critical") | D13: =COUNTIFS(Tracker!$B$2:$B$106,A13,Tracker!$E$2:$E$106,"High") | E13: =COUNTIFS(Tracker!$B$2:$B$106,A13,Tracker!$E$2:$E$106,"Medium") | F13: =COUNTIFS(Tracker!$B$2:$B$106,A13,Tracker!$F$2:$F$106,"Done")+COUNTIFS(Tracker!$B$2:$B$106,A13,Tracker!$F$2:$F$106,"QA Complete") | G13: =B13-F13
A14: Broken Workflow Fixes | B14: =COUNTIF(Tracker!$B$2:$B$106,A14) | C14: =COUNTIFS(Tracker!$B$2:$B$106,A14,Tracker!$E$2:$E$106,"Critical") | D14: =COUNTIFS(Tracker!$B$2:$B$106,A14,Tracker!$E$2:$E$106,"High") | E14: =COUNTIFS(Tracker!$B$2:$B$106,A14,Tracker!$E$2:$E$106,"Medium") | F14: =COUNTIFS(Tracker!$B$2:$B$106,A14,Tracker!$F$2:$F$106,"Done")+COUNTIFS(Tracker!$B$2:$B$106,A14,Tracker!$F$2:$F$106,"QA Complete") | G14: =B14-F14
A15: Codebase Cleanup | B15: =COUNTIF(Tracker!$B$2:$B$106,A15) | C15: =COUNTIFS(Tracker!$B$2:$B$106,A15,Tracker!$E$2:$E$106,"Critical") | D15: =COUNTIFS(Tracker!$B$2:$B$106,A15,Tracker!$E$2:$E$106,"High") | E15: =COUNTIFS(Tracker!$B$2:$B$106,A15,Tracker!$E$2:$E$106,"Medium") | F15: =COUNTIFS(Tracker!$B$2:$B$106,A15,Tracker!$F$2:$F$106,"Done")+COUNTIFS(Tracker!$B$2:$B$106,A15,Tracker!$F$2:$F$106,"QA Complete") | G15: =B15-F15
A16: Engineering Discipline | B16: =COUNTIF(Tracker!$B$2:$B$106,A16) | C16: =COUNTIFS(Tracker!$B$2:$B$106,A16,Tracker!$E$2:$E$106,"Critical") | D16: =COUNTIFS(Tracker!$B$2:$B$106,A16,Tracker!$E$2:$E$106,"High") | E16: =COUNTIFS(Tracker!$B$2:$B$106,A16,Tracker!$E$2:$E$106,"Medium") | F16: =COUNTIFS(Tracker!$B$2:$B$106,A16,Tracker!$F$2:$F$106,"Done")+COUNTIFS(Tracker!$B$2:$B$106,A16,Tracker!$F$2:$F$106,"QA Complete") | G16: =B16-F16
A17: Immediate Stabilization | B17: =COUNTIF(Tracker!$B$2:$B$106,A17) | C17: =COUNTIFS(Tracker!$B$2:$B$106,A17,Tracker!$E$2:$E$106,"Critical") | D17: =COUNTIFS(Tracker!$B$2:$B$106,A17,Tracker!$E$2:$E$106,"High") | E17: =COUNTIFS(Tracker!$B$2:$B$106,A17,Tracker!$E$2:$E$106,"Medium") | F17: =COUNTIFS(Tracker!$B$2:$B$106,A17,Tracker!$F$2:$F$106,"Done")+COUNTIFS(Tracker!$B$2:$B$106,A17,Tracker!$F$2:$F$106,"QA Complete") | G17: =B17-F17
A18: Logic Extraction | B18: =COUNTIF(Tracker!$B$2:$B$106,A18) | C18: =COUNTIFS(Tracker!$B$2:$B$106,A18,Tracker!$E$2:$E$106,"Critical") | D18: =COUNTIFS(Tracker!$B$2:$B$106,A18,Tracker!$E$2:$E$106,"High") | E18: =COUNTIFS(Tracker!$B$2:$B$106,A18,Tracker!$E$2:$E$106,"Medium") | F18: =COUNTIFS(Tracker!$B$2:$B$106,A18,Tracker!$F$2:$F$106,"Done")+COUNTIFS(Tracker!$B$2:$B$106,A18,Tracker!$F$2:$F$106,"QA Complete") | G18: =B18-F18
A19: Production Readiness | B19: =COUNTIF(Tracker!$B$2:$B$106,A19) | C19: =COUNTIFS(Tracker!$B$2:$B$106,A19,Tracker!$E$2:$E$106,"Critical") | D19: =COUNTIFS(Tracker!$B$2:$B$106,A19,Tracker!$E$2:$E$106,"High") | E19: =COUNTIFS(Tracker!$B$2:$B$106,A19,Tracker!$E$2:$E$106,"Medium") | F19: =COUNTIFS(Tracker!$B$2:$B$106,A19,Tracker!$F$2:$F$106,"Done")+COUNTIFS(Tracker!$B$2:$B$106,A19,Tracker!$F$2:$F$106,"QA Complete") | G19: =B19-F19
A20: Project Boundaries | B20: =COUNTIF(Tracker!$B$2:$B$106,A20) | C20: =COUNTIFS(Tracker!$B$2:$B$106,A20,Tracker!$E$2:$E$106,"Critical") | D20: =COUNTIFS(Tracker!$B$2:$B$106,A20,Tracker!$E$2:$E$106,"High") | E20: =COUNTIFS(Tracker!$B$2:$B$106,A20,Tracker!$E$2:$E$106,"Medium") | F20: =COUNTIFS(Tracker!$B$2:$B$106,A20,Tracker!$F$2:$F$106,"Done")+COUNTIFS(Tracker!$B$2:$B$106,A20,Tracker!$F$2:$F$106,"QA Complete") | G20: =B20-F20
A21: Repo Hygiene | B21: =COUNTIF(Tracker!$B$2:$B$106,A21) | C21: =COUNTIFS(Tracker!$B$2:$B$106,A21,Tracker!$E$2:$E$106,"Critical") | D21: =COUNTIFS(Tracker!$B$2:$B$106,A21,Tracker!$E$2:$E$106,"High") | E21: =COUNTIFS(Tracker!$B$2:$B$106,A21,Tracker!$E$2:$E$106,"Medium") | F21: =COUNTIFS(Tracker!$B$2:$B$106,A21,Tracker!$F$2:$F$106,"Done")+COUNTIFS(Tracker!$B$2:$B$106,A21,Tracker!$F$2:$F$106,"QA Complete") | G21: =B21-F21
A22: Runtime Stability | B22: =COUNTIF(Tracker!$B$2:$B$106,A22) | C22: =COUNTIFS(Tracker!$B$2:$B$106,A22,Tracker!$E$2:$E$106,"Critical") | D22: =COUNTIFS(Tracker!$B$2:$B$106,A22,Tracker!$E$2:$E$106,"High") | E22: =COUNTIFS(Tracker!$B$2:$B$106,A22,Tracker!$E$2:$E$106,"Medium") | F22: =COUNTIFS(Tracker!$B$2:$B$106,A22,Tracker!$F$2:$F$106,"Done")+COUNTIFS(Tracker!$B$2:$B$106,A22,Tracker!$F$2:$F$106,"QA Complete") | G22: =B22-F22
A23: Security & Config | B23: =COUNTIF(Tracker!$B$2:$B$106,A23) | C23: =COUNTIFS(Tracker!$B$2:$B$106,A23,Tracker!$E$2:$E$106,"Critical") | D23: =COUNTIFS(Tracker!$B$2:$B$106,A23,Tracker!$E$2:$E$106,"High") | E23: =COUNTIFS(Tracker!$B$2:$B$106,A23,Tracker!$E$2:$E$106,"Medium") | F23: =COUNTIFS(Tracker!$B$2:$B$106,A23,Tracker!$F$2:$F$106,"Done")+COUNTIFS(Tracker!$B$2:$B$106,A23,Tracker!$F$2:$F$106,"QA Complete") | G23: =B23-F23
A24: State & Mutations | B24: =COUNTIF(Tracker!$B$2:$B$106,A24) | C24: =COUNTIFS(Tracker!$B$2:$B$106,A24,Tracker!$E$2:$E$106,"Critical") | D24: =COUNTIFS(Tracker!$B$2:$B$106,A24,Tracker!$E$2:$E$106,"High") | E24: =COUNTIFS(Tracker!$B$2:$B$106,A24,Tracker!$E$2:$E$106,"Medium") | F24: =COUNTIFS(Tracker!$B$2:$B$106,A24,Tracker!$F$2:$F$106,"Done")+COUNTIFS(Tracker!$B$2:$B$106,A24,Tracker!$F$2:$F$106,"QA Complete") | G24: =B24-F24
... A28: Workflow Continuity | B28: =COUNTIF(Tracker!$B$2:$B$106,A28) | C28: =COUNTIFS(Tracker!$B$2:$B$106,A28,Tracker!$E$2:$E$106,"Critical") | D28: =COUNTIFS(Tracker!$B$2:$B$106,A28,Tracker!$E$2:$E$106,"High") | E28: =COUNTIFS(Tracker!$B$2:$B$106,A28,Tracker!$E$2:$E$106,"Medium") | F28: =COUNTIFS(Tracker!$B$2:$B$106,A28,Tracker!$F$2:$F$106,"Done")+COUNTIFS(Tracker!$B$2:$B$106,A28,Tracker!$F$2:$F$106,"QA Complete") | G28: =B28-F28

Sheet MSP Import
A1: Outline Level | B1: Summary | C1: Task Name | D1: Owner | E1: Priority | F1: Status | G1: Start | H1: Finish | I1: Duration (days)
A2: 1 | B2: Yes | C2: Immediate Stabilization | D2: 18 | E2: 18 | F2: 18 | G2: 46111 | H2: 46122 | I2: 12
A3: 2 | B3: No | C3: Identify every duplicated module under src/<module> and src/components/<module> | D3: Engineering | E3: Critical | F3: Done | G3: 46111 | H3: 46115 | I3: 5
A4: 2 | B4: No | C4: Choose one canonical location for each duplicated file | D4: Engineering | E4: Critical | F4: Done | G4: 46111 | H4: 46115 | I4: 5
A5: 2 | B5: No | C5: Replace duplicate copies with imports/re-exports temporarily | D5: Engineering | E5: Critical | F5: Done | G5: 46111 | H5: 46115 | I5: 5
A6: 2 | B6: No | C6: Delete stale duplicate implementations after verification | D6: Engineering | E6: High | F6: Done | G6: 46118 | H6: 46122 | I6: 5
A7: 2 | B7: No | C7: Document final folder ownership rules | D7: Engineering | E7: High | F7: Done | G7: 46118 | H7: 46122 | I7: 5
A8: 1 | B8: Yes | C8: Broken Workflow Fixes | D8: 18 | E8: 18 | F8: 18 | G8: 46111 | H8: 46115 | I8: 5
A9: 2 | B9: No | C9: Confirm task creation no longer causes disappearing records | D9: Engineering / QA | E9: Critical | F9: Done | G9: 46111 | H9: 46115 | I9: 5
A10: 2 | B10: No | C10: Fix cost codes save behavior | D10: Engineering | E10: Critical | F10: Done | G10: 46111 | H10: 46115 | I10: 5
A11: 2 | B11: No | C11: Fix contracts save behavior | D11: Engineering | E11: Critical | F11: Done | G11: 46111 | H11: 46115 | I11: 5
A12: 2 | B12: No | C12: Fix change order edit behavior | D12: Engineering | E12: Critical | F12: Done | G12: 46111 | H12: 46115 | I12: 5
A13: 2 | B13: No | C13: Fix change order delete behavior | D13: Engineering | E13: Critical | F13: Done | G13: 46111 | H13: 46115 | I13: 5
... A122: 2 | B122: No | C122: Re-check UI trust and silent failure risk | D122: QA / PM | E122: High | F122: Done | G122: 46139 | H122: 46143 | I122: 5

Sheet Notes
A1: Usage
A3: Excel:
A4: Use the Tracker sheet as the working checklist.
A6: Microsoft Project:
A7: Use the companion XML file in this deliverable for direct import into Microsoft Project.
A8: The MSP Import sheet mirrors the same task hierarchy and dates for quick reference.
A10: Scheduling assumptions:
A11: Plan start = Mar 30, 2026.
A12: Week 1..5 map to Monday-start / Friday-target weekly buckets.
A13: Each detailed task is set to a 5-day window for import simplicity.
A15: Status update — July 23, 2026
A16: Only tasks with direct GitHub PR, test, CI, or runbook evidence were marked Done. Broad security, workflow, project-boundary, backup/recovery, and full end-to-end readiness items remain open until their complete acceptance criteria are proven.
